{
  "sapient":{
    "display":"Sapient",
    "alignment":1,
    "moveLand":true,
    "moveWater":false,
    "moveAir":false,
    "moveWalls":false,
    "actionPoints":1,
    "str":5.0,
    "agil":5.0,
    "vit":5.0,
    "intel":5.0,
    "will":5.0,
    "moraleNorm":60,
    "moraleMax":100,
    "restMax":72,
    "foodMax":30,
    "waterMax":30,
    "naturalArmor":0,
    "skills":[],
    "spriteSheet":"graphic/fighter_sheet.png",
    "spriteWidth":16,
    "spriteHeight":18,
    "sheetCols":9,
    "sheetRows":4
  },
  "insect":{
    "display": "Insect",
    "alignment":1,
    "moveLand":true,
    "moveWater":false,
    "moveAir":false,
    "moveWalls":false,
    "actionPoints":1,
    "str": 3.0,
    "agil": 3.0,
    "vit": 3.0,
    "intel": 0.0,
    "will": 0.0,
    "moraleNorm":60,
    "moraleMax":100,
    "restMax":72,
    "foodMax":30,
    "waterMax":30,
    "naturalArmor":5,
    "skills": ["poisonBite","poisonSpit","burrow"],
    "spriteSheet":"graphic/centipede_01.png",
    "spriteWidth":16,
    "spriteHeight":16,
    "sheetCols":2,
    "sheetRows":3
  },
  "daemon":{
    "display":"Daemon",
    "alignment":2,
    "moveType":1,
    "actionPoints":1,
    "str":10.0,
    "agil":10.0,
    "vit":10.0,
    "intel":10.0,
    "will":10.0,
    "moraleNorm":60,
    "moraleMax":100,
    "restMax":72,
    "hungerMax":30,
    "thirstMax":30,
    "naturalArmor":10,
    "skills":[],
    "spriteSheet":"graphic/daemon_sheet.png",
    "spriteWidth":16,
    "spriteHeight":18,
    "sheetCols":9,
    "sheetRows":4
  }
}
